{
  "Spider-Man: Homecoming": {
    "json_class": "Movie",
    "name": "Spider-Man: Homecoming",
    "url": "https://en.wikipedia.org/wiki/Spider-Man:_Homecoming",
    "actors": [
      "Tom Holland",
      "Michael Keaton",
      "Jon Favreau",
      "Zendaya",
      "Donald Glover",
      "Tyne Daly",
      "Marisa Tomei",
      "Robert Downey Jr."
    ],
    "box_office": 8,
    "year": "2017"
  },
  "Avengers: Endgame": {
    "json_class": "Movie",
    "name": "Avengers: Endgame",
    "url": "https://en.wikipedia.org/wiki/Avengers:_Endgame",
    "actors": [
      "Robert Downey Jr.",
      "Chris Hemsworth",
      "Mark Ruffalo",
      "Chris Evans",
      "Scarlett Johansson",
      "Benedict Cumberbatch",
      "Don Cheadle",
      "Tom Holland",
      "Chadwick Boseman",
      "Paul Bettany",
      "Elizabeth Olsen",
      "Anthony Mackie",
      "Sebastian Stan",
      "Letitia Wright",
      "Dave Bautista",
      "Zoe Saldana",
      "Josh Brolin",
      "Chris Pratt",
      "Jeremy Renner",
      "Evangeline Lilly",
      "Jon Favreau",
      "Paul Rudd",
      "Brie Larson"
    ],
    "box_office": null,
    "year": "2019"
  },
  "Knives Out": {
    "json_class": "Movie",
    "name": "Knives Out",
    "url": "https://en.wikipedia.org/wiki/Knives_Out_(film)",
    "actors": [
      "Daniel Craig",
      "Chris Evans",
      "Lakeith Stanfield",
      "Michael Shannon",
      "Ana de Armas",
      "Don Johnson",
      "Jamie Lee Curtis",
      "Toni Collette",
      "Christopher Plummer"
    ],
    "box_office": null,
    "year": "2019"
  },
  "The Red Sea Diving Resort": {
    "json_class": "Movie",
    "name": "The Red Sea Diving Resort",
    "url": "https://en.wikipedia.org/wiki/The_Red_Sea_Diving_Resort",
    "actors": [
      "Chris Evans",
      "Haley Bennett",
      "Michael K. Williams",
      "Michiel Huisman",
      "Alessandro Nivola",
      "Greg Kinnear",
      "Ben Kingsley"
    ],
    "box_office": null,
    "year": null
  },
  "Chris Evans": {
    "json_class": "Actor",
    "name": "Chris Evans",
    "movies": [
      "The Newcomers",
      "Not Another Teen Movie",
      "The Perfect Score",
      "Cellular",
      "Fierce People",
      "Fantastic Four",
      "London",
      "TMNT",
      "Sunshine",
      "Fantastic Four: Rise of the Silver Surfer",
      "The Nanny Diaries",
      "Battle for Terra",
      "Street Kings",
      "The Loss of a Teardrop Diamond",
      "Push",
      "The Losers",
      "Scott Pilgrim vs. the World",
      "Puncture",
      "Captain America: The First Avenger",
      "What's Your Number?",
      "The Avengers",
      "The Iceman",
      "Snowpiercer",
      "Thor: The Dark World",
      "Captain America: The Winter Soldier",
      "Before We Go",
      "Avengers: Age of Ultron",
      "Ant-Man",
      "Playing It Cool",
      "Captain America: Civil War",
      "Gifted",
      "Spider-Man: Homecoming",
      "Avengers: Infinity War",
      "Avengers: Endgame",
      "Knives Out",
      "The Red Sea Diving Resort"
    ]
  },
  "Benedict Cumberbatch": {
    "json_class": "Actor",
    "name": "Benedict Cumberbatch",
    "movies": [
      "Benedict Cumberbatch"
    ]
  },
  "Don Cheadle": {
    "json_class": "Actor",
    "name": "Don Cheadle",
    "movies": [
      "Moving Violations",
      "Hamburger Hill",
      "Colors",
      "Roadside Prophets",
      "The Meteor Man",
      "Things to Do in Denver When You're Dead",
      "Devil in a Blue Dress",
      "Rebound: The Legend of Earl \"The Goat\" Manigault",
      "Volcano",
      "Rosewood",
      "Boogie Nights",
      "Out of Sight",
      "The Rat Pack",
      "Bulworth",
      "Traffic",
      "Mission to Mars",
      "The Family Man",
      "Rush Hour 2",
      "Things Behind the Sun",
      "Manic",
      "Swordfish",
      "Ticker",
      "Ocean's Eleven",
      "Abby Singer",
      "The United States of Leland",
      "Ocean's Twelve",
      "After the Sunset",
      "The Assassination of Richard Nixon",
      "citation needed",
      "Hotel Rwanda",
      "Crash",
      "The Dog Problem",
      "King Leopold's Ghost",
      "Reign Over Me",
      "Talk to Me",
      "Ocean's Thirteen",
      "Darfur Now",
      "Traitor",
      "Hotel for Dogs",
      "The People Speak",
      "Brooklyn's Finest",
      "Iron Man 2",
      "The Guard",
      "Flight",
      "Iron Man 3",
      null,
      "Miles Ahead",
      null,
      "Kevin Hart: What Now?",
      "Avengers: Infinity War",
      "Avengers: Endgame",
      "Prince of Darkness"
    ]
  },
  "Tom Holland": {
    "json_class": "Actor",
    "name": "Tom Holland",
    "movies": [
      "Arrietty",
      "The Impossible",
      "How I Live Now",
      "Locke",
      "In the Heart of the Sea",
      "Captain America: Civil War",
      "Pilgrimage",
      "Samuel Insull",
      "Avengers: Infinity War",
      "Avengers: Endgame",
      "Todd Hewitt",
      "The Voyage of Doctor Dolittle"
    ]
  }
}